valyu_haystack/__about__.py
valyu_haystack/__init__.py
valyu_haystack/components/__init__.py
valyu_haystack/components/valyu_content_fetcher.py
valyu_haystack/components/valyu_search.py
valyu_search_haystack-0.1.1.dist-info/METADATA
valyu_search_haystack-0.1.1.dist-info/WHEEL
valyu_search_haystack-0.1.1.dist-info/licenses/LICENSE
valyu_search_haystack-0.1.1.dist-info/RECORD
