Metadata-Version: 2.4
Name: valyu-search-haystack
Version: 0.1.1
Summary: Haystack components for integrating Valyu's search and content extraction APIs
Project-URL: Documentation, https://github.com/valyu-network/valyu-search-haystack#readme
Project-URL: Issues, https://github.com/valyu-network/valyu-search-haystack/issues
Project-URL: Source, https://github.com/valyu-network/valyu-search-haystack
Author-email: Valyu <support@valyu.com>
License: Apache License
License-File: LICENSE
Keywords: content-extraction,haystack,llm,rag,search,valyu
Classifier: Development Status :: 4 - Beta
Classifier: Intended Audience :: Developers
Classifier: License :: OSI Approved :: Apache Software License
Classifier: Programming Language :: Python
Classifier: Programming Language :: Python :: 3.8
Classifier: Programming Language :: Python :: 3.9
Classifier: Programming Language :: Python :: 3.10
Classifier: Programming Language :: Python :: 3.11
Classifier: Programming Language :: Python :: 3.12
Classifier: Programming Language :: Python :: Implementation :: CPython
Classifier: Topic :: Software Development :: Libraries :: Python Modules
Requires-Python: >=3.8
Requires-Dist: haystack-ai>=2.0.0
Requires-Dist: valyu>=2.2.1
Provides-Extra: dev
Requires-Dist: black>=23.0; extra == 'dev'
Requires-Dist: mypy>=1.0; extra == 'dev'
Requires-Dist: pytest-cov>=4.0; extra == 'dev'
Requires-Dist: pytest>=7.0; extra == 'dev'
Requires-Dist: ruff>=0.1.0; extra == 'dev'
